pylinefinder/__main__.py
pylinefinder-0.1.6.dist-info/METADATA
pylinefinder-0.1.6.dist-info/WHEEL
pylinefinder-0.1.6.dist-info/RECORD
