Metadata-Version: 2.1
Name: pylinefinder
Version: 0.1.6
Summary: 
Author: Antonio
Author-email: antoniofernandodj@outlook.com
Requires-Python: >=3.10,<4.0
Classifier: Programming Language :: Python :: 3
Classifier: Programming Language :: Python :: 3.10
Classifier: Programming Language :: Python :: 3.11
Requires-Dist: click (>=8.1.4,<9.0.0)
